ai_code_review/__init__.py
ai_code_review/cli.py
ai_code_review/core/__init__.py
ai_code_review/core/base_platform_client.py
ai_code_review/core/forgejo_client.py
ai_code_review/core/github_client.py
ai_code_review/core/gitlab_client.py
ai_code_review/core/local_git_client.py
ai_code_review/core/review_engine.py
ai_code_review/models/__init__.py
ai_code_review/models/config.py
ai_code_review/models/platform.py
ai_code_review/models/review.py
ai_code_review/models/settings_sources.py
ai_code_review/providers/__init__.py
ai_code_review/providers/anthropic.py
ai_code_review/providers/anthropic_vertex.py
ai_code_review/providers/base.py
ai_code_review/providers/gemini.py
ai_code_review/providers/gemini_vertex.py
ai_code_review/providers/ollama.py
ai_code_review/providers/openai.py
ai_code_review/utils/__init__.py
ai_code_review/utils/constants.py
ai_code_review/utils/exceptions.py
ai_code_review/utils/platform_exceptions.py
ai_code_review/utils/prompts.py
ai_code_review/utils/ssl_utils.py
ai_code_review/utils/templates.py
ai_code_review/utils/validation.py
ai_code_review/utils/review_templates/local_review.md.j2
ai_code_review/utils/review_templates/remote_review.md.j2
context_generator/__init__.py
context_generator/cli.py
context_generator/constants.py
context_generator/models.py
context_generator/core/__init__.py
context_generator/core/code_extractor.py
context_generator/core/context_builder.py
context_generator/core/facts_extractor.py
context_generator/core/llm_analyzer.py
context_generator/providers/__init__.py
context_generator/providers/ci_docs_provider.py
context_generator/providers/context7_provider.py
context_generator/sections/__init__.py
context_generator/sections/base_section.py
context_generator/sections/ci_docs_section.py
context_generator/sections/context7_section.py
context_generator/sections/overview_section.py
context_generator/sections/review_section.py
context_generator/sections/structure_section.py
context_generator/sections/tech_stack_section.py
ai_code_review_cli-2.4.0.dist-info/METADATA
ai_code_review_cli-2.4.0.dist-info/WHEEL
ai_code_review_cli-2.4.0.dist-info/entry_points.txt
ai_code_review_cli-2.4.0.dist-info/licenses/LICENSE
ai_code_review_cli-2.4.0.dist-info/RECORD
