Metadata-Version: 2.4
Name: ai-code-review-cli
Version: 2.4.0
Summary: AI-powered code review tool with local Git, remote MR/PR analysis, and CI integration (GitLab, GitHub or Forgejo)
Project-URL: Homepage, https://gitlab.com/redhat/edge/ci-cd/ai-code-review
Project-URL: Repository, https://gitlab.com/redhat/edge/ci-cd/ai-code-review
Project-URL: Issues, https://gitlab.com/redhat/edge/ci-cd/ai-code-review/-/issues
Author-email: Juanje Ojeda <juanje@redhat.com>
License-Expression: MIT
License-File: LICENSE
Keywords: ai,assistant,automation,code quality,code review,coding,developer tools,devops,git,github,github actions,gitlab,gitlab-ci,llm,static code analysis,workflows
Classifier: Development Status :: 5 - Production/Stable
Classifier: Environment :: Console
Classifier: Intended Audience :: Developers
Classifier: License :: OSI Approved :: MIT License
Classifier: Programming Language :: Python :: 3
Classifier: Programming Language :: Python :: 3.12
Requires-Python: >=3.12
Requires-Dist: aiofiles>=23.2.0
Requires-Dist: aiohttp>=3.9.0
Requires-Dist: anthropic<1.0.0,>=0.40.0
Requires-Dist: click>=8.1.0
Requires-Dist: defusedxml>=0.7.1
Requires-Dist: gitpython>=3.1.40
Requires-Dist: grpcio>=1.75.0
Requires-Dist: httpx>=0.28.1
Requires-Dist: jinja2<4.0.0,>=3.1.0
Requires-Dist: langchain-anthropic<2.0.0,>=1.0.0
Requires-Dist: langchain-google-genai<5.0.0,>=4.0.0
Requires-Dist: langchain-google-vertexai<4.0.0,>=3.0.0
Requires-Dist: langchain-ollama<2.0.0,>=1.0.0
Requires-Dist: langchain-openai<1.0.0,>=0.3.0
Requires-Dist: langchain<3.0.0,>=1.0.0
Requires-Dist: ollama>=0.2.0
Requires-Dist: protobuf>=6.0.0
Requires-Dist: pydantic-core<3.0.0,>=2.33.0
Requires-Dist: pydantic-settings>=2.10.1
Requires-Dist: pydantic<3.0.0,>=2.12.0
Requires-Dist: pyforgejo>=2.0.0
Requires-Dist: pygithub>=2.1.0
Requires-Dist: python-gitlab>=7.0.0
Requires-Dist: pyyaml>=6.0.0
Requires-Dist: structlog>=23.2.0
Requires-Dist: unidiff>=0.7.0
Provides-Extra: dev
Requires-Dist: mypy>=1.19.0; extra == 'dev'
Requires-Dist: pytest-asyncio>=0.21.0; extra == 'dev'
Requires-Dist: pytest-cov>=4.1.0; extra == 'dev'
Requires-Dist: pytest-httpx>=0.30.0; extra == 'dev'
Requires-Dist: pytest-mock>=3.11.0; extra == 'dev'
Requires-Dist: pytest>=9.0.0; extra == 'dev'
Requires-Dist: ruff>=0.14.0; extra == 'dev'
Requires-Dist: types-pyyaml; extra == 'dev'
Requires-Dist: types-requests; extra == 'dev'
